pixviz/__init__.py
pixviz/__main__.py
pixviz/main_gui.py
pixviz/proc.py
pixviz/roi.py
pixviz/ui_components.py
pixviz/ui_logging.py
pixviz-1.1.0.dist-info/LICENSE
pixviz-1.1.0.dist-info/METADATA
pixviz-1.1.0.dist-info/WHEEL
pixviz-1.1.0.dist-info/top_level.txt
pixviz-1.1.0.dist-info/RECORD
