Metadata-Version: 2.1
Name: pixviz
Version: 1.1.0
Summary: GUI for image sequences pixel analysis
Author-email: Yu-Ting Wei <ytsimon2004@gmail.com>
License: BSD 3-Clause License
Project-URL: Homepage, https://github.com/ytsimon2004/pixelviz
Project-URL: Repository, https://github.com/ytsimon2004/pixelviz
Project-URL: Issues, https://github.com/ytsimon2004/pixelviz/issues
Keywords: computer vision,image processing
Classifier: Programming Language :: Python :: 3.10
Classifier: License :: OSI Approved :: BSD License
Classifier: Natural Language :: English
Classifier: Operating System :: OS Independent
Classifier: Topic :: Scientific/Engineering
Classifier: Intended Audience :: Science/Research
Classifier: Typing :: Typed
Requires-Python: >=3.10
License-File: LICENSE
Requires-Dist: typing-extensions
Requires-Dist: PyQt6
Requires-Dist: qimage2ndarray
Requires-Dist: numpy
Requires-Dist: matplotlib
Requires-Dist: opencv-python
Requires-Dist: tqdm
